.hgignore
.hgtags
HISTORY.rst
README.rst
ToDo.txt
mercurial_bitbucketize.py
setup.py
tox.ini
experiments/sample.py
mercurial_bitbucketize.egg-info/PKG-INFO
mercurial_bitbucketize.egg-info/SOURCES.txt
mercurial_bitbucketize.egg-info/dependency_links.txt
mercurial_bitbucketize.egg-info/requires.txt
mercurial_bitbucketize.egg-info/top_level.txt
mercurial_bitbucketize.egg-info/zip-safe
tests/README.txt
tests/non_context-buggy.t
tests/non_context-crtopts.t
tests/non_context-dfltseq.t
tests/non_context-fullname.t
tests/run_tests.sh