Metadata-Version: 1.1
Name: mercurial-bitbucketize
Version: 0.9.4
Summary: Mercurial Bitbucketize Extension
Home-page: https://foss.heptapod.net/mercurial/mercurial-bitbucketize
Author: Marcin Kasperski
Author-email: Marcin.Kasperski@mekk.waw.pl
License: BSD
Keywords: mercurial hg bitbucket
Platform: UNKNOWN
Classifier: Development Status :: 4 - Beta
Classifier: Environment :: Console
Classifier: Intended Audience :: Developers
Classifier: License :: DFSG approved
Classifier: License :: OSI Approved :: BSD License
Classifier: Programming Language :: Python :: 2
Classifier: Programming Language :: Python :: 3
Classifier: Operating System :: OS Independent
Classifier: Topic :: Software Development :: Version Control
